chinadaily/__init__.py
chinadaily/chinadaily.py
chinadaily/cli.py
chinadaily/constants.py
chinadaily-0.2.1.dist-info/licenses/AUTHORS.rst
chinadaily-0.2.1.dist-info/licenses/LICENSE
chinadaily-0.2.1.dist-info/METADATA
chinadaily-0.2.1.dist-info/WHEEL
chinadaily-0.2.1.dist-info/entry_points.txt
chinadaily-0.2.1.dist-info/top_level.txt
chinadaily-0.2.1.dist-info/RECORD
