Metadata-Version: 2.4
Name: chinadaily
Version: 0.2.1
Summary: Download China Daily newspaper PDF
Home-page: https://github.com/yarving/chinadailyproject
Author: ChinaDaily
Author-email: yarving@qq.com
License: GNU General Public License v3
Keywords: chinadaily
Classifier: Development Status :: 2 - Pre-Alpha
Classifier: Intended Audience :: Developers
Classifier: License :: OSI Approved :: GNU General Public License v3 (GPLv3)
Classifier: Natural Language :: English
Classifier: Programming Language :: Python :: 3
Classifier: Programming Language :: Python :: 3.5
Classifier: Programming Language :: Python :: 3.6
Classifier: Programming Language :: Python :: 3.7
Classifier: Programming Language :: Python :: 3.8
Requires-Python: >=3.5
License-File: LICENSE
License-File: AUTHORS.rst
Requires-Dist: requests>=2.31.0
Requires-Dist: PyPDF2==1.26.0
Requires-Dist: beautifulsoup4==4.9.3
Requires-Dist: lxml==4.6.1
Dynamic: author
Dynamic: author-email
Dynamic: classifier
Dynamic: description
Dynamic: home-page
Dynamic: keywords
Dynamic: license
Dynamic: license-file
Dynamic: requires-dist
Dynamic: requires-python
Dynamic: summary
